unitypython/CLI.py
unitypython/Collections.py
unitypython/IntEncode.py
unitypython/JSON.py
unitypython/Scoper.py
unitypython/Symtable.py
unitypython/TraffyAsm.py
unitypython/Transpile.py
unitypython/__init__.py
unitypython/__main__.py
unitypython-0.2.1.dist-info/METADATA
unitypython-0.2.1.dist-info/WHEEL
unitypython-0.2.1.dist-info/entry_points.txt
unitypython-0.2.1.dist-info/top_level.txt
unitypython-0.2.1.dist-info/RECORD
