Metadata-Version: 2.1
Name: unitypython
Version: 0.2.1
Summary: UNKNOWN
Home-page: https://github.com/thautwarm/Traffy.UnityPython
Author: thautwarm
Author-email: twshere@outlook.com
License: mit
Platform: any
Classifier: Programming Language :: Python :: 3.8
Classifier: Programming Language :: Python :: 3.9
Classifier: Programming Language :: Python :: 3.10
Classifier: Programming Language :: Python :: Implementation :: CPython
Requires-Python: >=3.8.0
Requires-Dist: wisepy2 (>=1.2.1)
